.gitignore
CHANGELOG.rst
LICENSE.txt
README.md
pyproject.toml
tox.ini
.github/workflows/sdist.yml
.github/workflows/tox.yml
src/obi_auth/__init__.py
src/obi_auth/cache.py
src/obi_auth/cli.py
src/obi_auth/client.py
src/obi_auth/config.py
src/obi_auth/exception.py
src/obi_auth/request.py
src/obi_auth/server.py
src/obi_auth/storage.py
src/obi_auth/typedef.py
src/obi_auth/util.py
src/obi_auth.egg-info/PKG-INFO
src/obi_auth.egg-info/SOURCES.txt
src/obi_auth.egg-info/dependency_links.txt
src/obi_auth.egg-info/entry_points.txt
src/obi_auth.egg-info/requires.txt
src/obi_auth.egg-info/top_level.txt
src/obi_auth/flows/__init__.py
src/obi_auth/flows/daf.py
src/obi_auth/flows/persistent_token.py
src/obi_auth/flows/pkce.py
tests/__init__.py
tests/daf.sh
tests/unit/__init__.py
tests/unit/conftest.py
tests/unit/test_cache.py
tests/unit/test_cli.py
tests/unit/test_client.py
tests/unit/test_config.py
tests/unit/test_server.py
tests/unit/test_storage.py
tests/unit/test_util.py
tests/unit/data/.gitignore
tests/unit/flows/test_daf.py
tests/unit/flows/test_persistent_token.py
tests/unit/flows/test_pkce.py