Metadata-Version: 2.4
Name: obi_auth
Version: 1.0.0
Summary: Python library for retrieving Keycloak access tokens interactively
Author-email: Open Brain Institute <info@openbraininstitute.org>
Maintainer-email: Open Brain Institute <info@openbraininstitute.org>
License: Apache-2.0
Project-URL: documentation, https://github.com/openbraininstitute/obi-auth
Project-URL: repository, https://github.com/openbraininstitute/obi-auth
Project-URL: changelog, https://github.com/openbraininstitute/obi-auth/CHANGELOG.rst
Classifier: Programming Language :: Python :: 3.11
Classifier: Programming Language :: Python :: 3.12
Classifier: Programming Language :: Python :: 3.13
Requires-Python: >=3.11
License-File: LICENSE.txt
Requires-Dist: click
Requires-Dist: cryptography>=3.0
Requires-Dist: fastapi
Requires-Dist: httpx
Requires-Dist: pydantic
Requires-Dist: pydantic-settings
Requires-Dist: pyjwt
Requires-Dist: uvicorn
Provides-Extra: notebook
Requires-Dist: rich; extra == "notebook"
Dynamic: license-file
